smartwatts/__init__.py
smartwatts/__main__.py
smartwatts/actor/__init__.py
smartwatts/actor/actor.py
smartwatts/actor/config.py
smartwatts/actor/factory.py
smartwatts/cli/__init__.py
smartwatts/cli/config_validator.py
smartwatts/exceptions.py
smartwatts/handler/__init__.py
smartwatts/handler/hwpc_report.py
smartwatts/model/__init__.py
smartwatts/model/cpu_topology.py
smartwatts/model/frequency_layer.py
smartwatts/model/power_model.py
smartwatts/model/sample_history.py
smartwatts-2.4.1.dist-info/WHEEL
smartwatts-2.4.1.dist-info/METADATA
smartwatts-2.4.1.dist-info/RECORD
