Metadata-Version: 2.3
Name: smartwatts
Version: 2.4.1
Summary: SmartWatts is a formula for a self-adaptive software-defined power meter based on the PowerAPI framework.
Keywords: powerapi,energy,power-meter,power-model,green-computing,containers
Author: Guillaume Fieni
Author-email: Guillaume Fieni <guillaume.fieni@inria.fr>
License: BSD-3-Clause
Classifier: Programming Language :: Python :: 3.10
Classifier: Programming Language :: Python :: 3.11
Classifier: Programming Language :: Python :: 3.12
Classifier: Programming Language :: Python :: 3.13
Classifier: License :: OSI Approved :: BSD License
Classifier: Intended Audience :: Science/Research
Classifier: Intended Audience :: Developers
Classifier: Intended Audience :: System Administrators
Classifier: Development Status :: 5 - Production/Stable
Classifier: Topic :: System :: Monitoring
Requires-Dist: powerapi[everything]==2.10.0
Requires-Dist: scikit-learn>=0.20.2
Requires-Python: >=3.10
Project-URL: documentation, https://powerapi.readthedocs.org
Project-URL: homepage, https://powerapi.org
Project-URL: repository, https://github.com/powerapi-ng/smartwatts-formula
